Workbook

Sheet Inputs
A1: MB143 Labour Calculation - Inputs
A2: Blue = stored/input value. Change a blue cell and the Calculations sheet recalculates.
A4: Input | B4: Value | C4: Source | D4: Where it comes from
A5: Estimate / Type | B5: MB143 / MB | C5: [EL] EMPLOYEE_LABOUR | D5: link_number, typeid
A6: Task | B6: OVERHAUL | C6: [EL] EMPLOYEE_LABOUR | D6: task
A7: Cost centre | B7: 05H2 | C7: [EL] EMPLOYEE_LABOUR | D7: costcentre
A8: Labour definition | B8: COACH TECHNICIAN | C8: [EL] EMPLOYEE_LABOUR | D8: labour_defn
A9: Time Required (hours) | B9: 2 | C9: [EL] EMPLOYEE_LABOUR | D9: hrs_reqd = 2:00 (typed by user), shown as decimal hours
A10: Time Addition (hours) | B10: 2 | C10: [EL] EMPLOYEE_LABOUR | D10: time_addition (stored; packages only read it)
A11: Wrench time stored, old row (H:MM as decimal hours) | B11: =1+33/60 -> 1.55 | C11: [EL] EMPLOYEE_LABOUR | D11: adj_hrs = 1:33 (old row)
A12: Usage % | B12: 100 | C12: [EL] EMPLOYEE_LABOUR | D12: usage
A13: Rate per hour | B13: 50.52 | C13: [ES] EMPLOYEE_SALARIES | D13: labour_defn -> EMPL_CLASS.wage_group -> rate_per_hour
A14: OVERHEAD | B14: 0.73 | C14: [CS] CES_SETTINGS | D14: parameter OVERHEAD
A15: NON_PRODUCTIVE_ADJUSTMENT | B15: 1.2 | C15: [CS] CES_SETTINGS | D15: parameter NON_PRODUCTIVE_ADJUSTMENT
A16: FRINGE | B16: 0.51 | C16: [CS] CES_SETTINGS | D16: parameter FRINGE
A17: BENEFIT | B17: 0 | C17: [CS] CES_SETTINGS | D17: parameter BENEFIT
A18: Material total (excl. tax) | B18: 639.08 | C18: Report | D18: Taken from your report; not recalculated. Assumes core cost = 0.

Sheet Calculations
A1: MB143 Labour Calculations (legacy CES packages vs new app)
A3: # | B3: Value | C3: Formula | D3: Inputs used | E3: Result | F3: Unit | G3: Formula with actual MB143 values | H3: How the final value is reached
A4: 1 | B4: Time in minutes | C4: HHMM_TO_MINUTES(time_addition) = hours x 60 | D4: [EL] time_addition | E4: =Inputs!$B$10*60 -> 120 | F4: min | G4: ="Time Addition "&TEXT(Inputs!$B$10,"0.00")&" h x 60 = "&TEXT(E4,"0")&" min" -> Time Addition 2.00 h x 60 = 120 min | H4: Time Addition is stored in decimal hours; multiply by 60 to get minutes.
A5: 2 | B5: Row labour cost | C5: rate x minutes x usage / 6000 | D5: [ES] rate, [EL] usage, step 1 | E5: =Inputs!$B$13*E4*Inputs!$B$12/6000 -> 101.04 | F5: $ | G5: ="$"&TEXT(Inputs!$B$13,"#,##0.00")&" x "&TEXT(E4,"0")&" min x "&TEXT(Inputs!$B$12,"0")&" / 6000 = "&"$"&TEXT(E5,"#,##0.00") -> $50.52 x 120 min x 100 / 6000 = $101.04 | H5: Rate per hour x minutes x usage, divided by 6000 (60 minutes x 100 percent). Equals rate x hours x usage%.
A6: 3 | B6: Extended (total) time | C6: ROUND(usage/100 x minutes) | D6: [EL] usage, step 1 | E6: =ROUND(Inputs!$B$12/100*E4,0) -> 120 | F6: min | G6: =TEXT(Inputs!$B$12,"0")&" / 100 x "&TEXT(E4,"0")&" min = "&TEXT(E6,"0")&" min" -> 100 / 100 x 120 min = 120 min | H6: Usage share of the minutes, rounded to whole minutes. This is the hours total in the summary.
A7: 4 | B7: Extended time as H:MM | C7: minutes / 60 : minutes mod 60 | D7: Step 3 | E7: =INT(E6/60)&":"&TEXT(MOD(E6,60),"00") -> 2:00 | F7: H:MM | G7: =TEXT(E6,"0")&" min / 60 = "&INT(E6/60)&" h remainder "&MOD(E6,60)&" min -> "&E7 -> 120 min / 60 = 2 h remainder 0 min -> 2:00 | H7: Whole hours = minutes / 60. Leftover minutes become the MM part.
A8: 5 | B8: Labour subtotal | C8: SUM of row costs (single row for MB143) | D8: Step 2 | E8: =E5 -> 101.04 | F8: $ | G8: ="Only one labour row, so subtotal = row cost "&"$"&TEXT(E5,"#,##0.00") -> Only one labour row, so subtotal = row cost $101.04 | H8: Add up the cost of every labour row on the estimate. MB143 has one row.
A9: 6 | B9: Labour overhead | C9: OVERHEAD x labour subtotal | D9: [CS] OVERHEAD, step 5 | E9: =ROUND(Inputs!$B$14*E8,2) -> 73.76 | F9: $ | G9: =TEXT(Inputs!$B$14,"0.00")&" x "&"$"&TEXT(E8,"#,##0.00")&" = "&"$"&TEXT(E9,"#,##0.00") -> 0.73 x $101.04 = $73.76 | H9: OVERHEAD setting (0.73) times the labour subtotal, rounded to 2 decimals. Fringe and benefits are not part of it.
A10: 7 | B10: Labour total (incl. overhead) | C10: subtotal + overhead | D10: Steps 5 and 6 | E10: =E8+E9 -> 174.8 | F10: $ | G10: ="$"&TEXT(E8,"#,##0.00")&" + "&"$"&TEXT(E9,"#,##0.00")&" = "&"$"&TEXT(E10,"#,##0.00") -> $101.04 + $73.76 = $174.80 | H10: Labour subtotal plus overhead.
A11: 8 | B11: Total cost (excl. tax) | C11: materials - core cost + labour total | D11: Material total, step 7 | E11: =Inputs!$B$18+E10 -> 813.88 | F11: $ | G11: ="$"&TEXT(Inputs!$B$18,"#,##0.00")&" materials + "&"$"&TEXT(E10,"#,##0.00")&" labour = "&"$"&TEXT(E11,"#,##0.00") -> $639.08 materials + $174.80 labour = $813.88 | H11: Material total plus labour total. Core cost is assumed to be 0, so nothing is deducted.
A12: 9 | B12: Wrench time, legacy report (minutes) | C12: ROUND(usage/100 x adj_hrs in minutes) | D12: [EL] adj_hrs, usage | E12: =ROUND(Inputs!$B$12/100*Inputs!$B$11*60,0) -> 93 | F12: min | G12: =TEXT(Inputs!$B$12,"0")&" / 100 x "&TEXT(Inputs!$B$11,"0.0000")&" h (1:33) x 60 = "&TEXT(E12,"0")&" min" -> 100 / 100 x 1.5500 h (1:33) x 60 = 93 min | H12: Stored adj_hrs (1:33 = 1 + 33/60 = 1.55 h), converted to minutes and scaled by usage.
A13: 10 | B13: Wrench time, legacy as H:MM | C13: minutes / 60 : minutes mod 60 | D13: Step 9 | E13: =INT(E12/60)&":"&TEXT(MOD(E12,60),"00") -> 1:33 | F13: H:MM | G13: =TEXT(E12,"0")&" min / 60 = "&INT(E12/60)&" h remainder "&MOD(E12,60)&" min -> "&E13 -> 93 min / 60 = 1 h remainder 33 min -> 1:33 | H13: Same hours and minutes split as step 4.
A14: 11 | B14: Wrench time, new app (minutes) | C14: ROUND(Time Required in minutes / NON_PRODUCTIVE_ADJUSTMENT) | D14: [EL] hrs_reqd, [CS] NON_PRODUCTIVE_ADJUSTMENT | E14: =ROUND(Inputs!$B$9*60/Inputs!$B$15,0) -> 100 | F14: min | G14: =TEXT(Inputs!$B$9,"0.00")&" h x 60 = "&TEXT(Inputs!$B$9*60,"0")&" min / "&TEXT(Inputs!$B$15,"0.00")&" = "&TEXT(Inputs!$B$9*60/Inputs!$B$15,"0.00")&" -> rounded "&TEXT(E14,"0")&" min" -> 2.00 h x 60 = 120 min / 1.20 = 100.00 -> rounded 100 min | H14: Required time in minutes divided by the non-productive adjustment, rounded to whole minutes. Saved to AdjHrs when a row is created or edited.
A15: 12 | B15: Wrench time, new app as H:MM (saved to AdjHrs) | C15: minutes / 60 : minutes mod 60 | D15: Step 11 | E15: =INT(E14/60)&":"&TEXT(MOD(E14,60),"00") -> 1:40 | F15: H:MM | G15: =TEXT(E14,"0")&" min / 60 = "&INT(E14/60)&" h remainder "&MOD(E14,60)&" min -> "&E15 -> 100 min / 60 = 1 h remainder 40 min -> 1:40 | H15: Same hours and minutes split as step 4. This value is stored in AdjHrs.
A16: 13 | B16: Fringe (currently OFF in SQL) | C16: Labour subtotal x FRINGE | D16: [CS] FRINGE, step 5 | E16: =ROUND(E8*Inputs!$B$16,2) -> 51.53 | F16: $ if enabled | G16: ="$"&TEXT(E8,"#,##0.00")&" x "&TEXT(Inputs!$B$16,"0.00")&" = "&"$"&TEXT(E16,"#,##0.00") -> $101.04 x 0.51 = $51.53 | H16: New app only. Labour subtotal times FRINGE. The SQL currently returns 0, so this adds nothing today.
A17: 14 | B17: Benefits (currently OFF in SQL) | C17: (Labour + Fringe) x BENEFIT | D17: [CS] BENEFIT, steps 5 and 13 | E17: =ROUND((E8+E16)*Inputs!$B$17,2) -> 0 | F17: $ if enabled | G17: ="("&"$"&TEXT(E8,"#,##0.00")&" + "&"$"&TEXT(E16,"#,##0.00")&") x "&TEXT(Inputs!$B$17,"0.00")&" = "&"$"&TEXT(E17,"#,##0.00") -> ($101.04 + $51.53) x 0.00 = $0.00 | H17: New app only. Fringe is added to labour first, then BENEFIT is applied to the sum. BENEFIT is 0.
A18: 15 | B18: Labour total if fringe and benefits enabled | C18: subtotal + fringe + benefits + overhead | D18: Steps 5, 6, 13, 14 | E18: =E8+E16+E17+E9 -> 226.33 | F18: $ | G18: ="$"&TEXT(E8,"#,##0.00")&" + "&"$"&TEXT(E16,"#,##0.00")&" + "&"$"&TEXT(E17,"#,##0.00")&" + "&"$"&TEXT(E9,"#,##0.00")&" = "&"$"&TEXT(E18,"#,##0.00") -> $101.04 + $51.53 + $0.00 + $73.76 = $226.33 | H18: Labour subtotal + fringe + benefits + overhead. Overhead stays on the base subtotal.
A19: 16 | B19: Total cost (excl. tax) if enabled | C19: materials + labour total with fringe/benefits | D19: Material total, step 15 | E19: =Inputs!$B$18+E18 -> 865.41 | F19: $ | G19: ="$"&TEXT(Inputs!$B$18,"#,##0.00")&" materials + "&"$"&TEXT(E18,"#,##0.00")&" labour = "&"$"&TEXT(E19,"#,##0.00") -> $639.08 materials + $226.33 labour = $865.41 | H19: Material total plus labour total with fringe and benefits. Shown for comparison only.
A21: Notes
A22: - | B22: Cost is driven by time_addition, not by hrs_reqd or wrench time. Wrench time never multiplies a rate.
A23: - | B23: Steps 2-4 mirror GET_LABOUR_COST; steps 5-8 mirror RPT_RBP_COST in the Oracle packages.
A24: - | B24: Old rows keep their stored AdjHrs (1:33 for MB143). New or edited rows follow step 11 (1:40).
A25: - | B25: Steps 13-16 are new-app only. The SQL currently returns 0 for fringe and benefit to match legacy.

Sheet Settings Usage
A1: CES_SETTINGS usage in the Oracle packages
A3: Setting (Parameter) | B3: Used in legacy package cost? | C3: Where in the packages | D3: New app today | E3: MB143 value
A4: OVERHEAD | B4: Yes | C4: RPT_RBP_COST: overhead = OVERHEAD x labour subtotal (INTERNAL_RB_PRICE calls it for the variance report). Older copy in RETRIEVE_RBP_TOTAL_COST is commented out. | D4: Used: Labour total x OVERHEAD | E4: =Inputs!$B$14 -> 0.73
A5: NON_PRODUCTIVE_ADJUSTMENT | B5: No (display only) | C5: RETRIEVE_MB_LABOUR returns it as a VALUE column. Never multiplied or divided in cost. | D5: Used only to calculate Wrench Time when a row is saved | E5: =Inputs!$B$15 -> 1.2
A6: FRINGE | B6: No | C6: Name not referenced in the packages. RETRIEVE_CES_SETTI can fetch any parameter, so the legacy client could have used it (unverified). | D6: Calculated in C# but forced to 0 by the labour SQL | E6: =Inputs!$B$16 -> 0.51
A7: BENEFIT | B7: No | C7: Name not referenced in the packages. Same caveat as FRINGE. | D7: Calculated in C# but forced to 0 by the labour SQL | E7: =Inputs!$B$17 -> 0
A8: TAX_RATE | B8: No | C8: Name not referenced. GET_MATERIAL_COST stores a separate taxable_cost, so the client most likely applied tax. | D8: Material total x TAX_RATE / 100; labour is not taxed | E8: n/a

Sheet Field Reference
A1: Labour fields: legacy CES vs new app
A3: Field | B3: Source column | C3: Legacy CES (packages) | D3: New app | E3: Drives cost?
A4: Time Required | B4: hrs_reqd (H:MM text) | C4: Shown in the labour grid. Not used in any calculation. | D4: Hours = H + MM/60 | E4: No
A5: Time (report) | B5: time_addition | C5: HHMM_TO_MINUTES(time_addition) = hours x 60, shown as H:MM | D5: TimeAddition hours; saved as Hrs + Mins/60 on create/edit | E5: Yes
A6: Usage % | B6: usage | C6: Stored value, commas replaced with dots | D6: Same | E6: Yes
A7: Extended / Effective Time | B7: time_addition, usage | C7: ROUND(usage/100 x HHMM_TO_MINUTES(time_addition)) | D7: Hours x Usage / 100 | E7: Reported hours
A8: Wrench Time (AdjHrs) | B8: adj_hrs (H:MM text) | C8: HHMM_TO_DECIMAL -> HHMM_TO_MINUTES -> ROUND(usage/100 x minutes), shown as H:MM. Display only. | D8: Saved: ROUND(Time Required minutes / NON_PRODUCTIVE_ADJUSTMENT) as H:MM. Reported as a numeric decimal-hours value. | E8: No
A9: Labour Type | B9: labour_type | C9: Stored; only returned by RETRIEVE_EMPLOYEE_LABOUR | D9: Looked up from EmplClass by labour definition on save | E9: No
A10: Hourly Rate | B10: EMPL_CLASS.wage_group, EMPLOYEE_SALARIES.rate_per_hour | C10: labour_defn = UPPER(EMPL_CLASS.labour_defn) -> wage_group -> rate | D10: Same lookup in SQL | E10: Yes
A11: Row Labour Cost | B11: time_addition, usage, rate | C11: rate x HHMM_TO_MINUTES(time_addition) x usage / 6000 | D11: TimeAddition x Usage/100 x Rate | E11: Yes
A12: Labour Overhead | B12: CES_SETTINGS OVERHEAD | C12: MAX(OVERHEAD) x labour subtotal | D12: Labour total x OVERHEAD | E12: Yes
A13: Fringe / Benefits | B13: CES_SETTINGS FRINGE, BENEFIT | C13: Not in the packages | D13: In C#, but forced to 0 by the labour SQL | E13: No (off)
A14: Fields not used in cost | B14: hrs_reqd, adj_hrs, labour_type, rebuilt_part_num, date_revised, costcentre, task, date_entered, last_modified_by; EMPL_CLASS.hrs_per_week, overheadtype, date_entered; EMPLOYEE_SALARIES.date_entered; USERS.use_overhead_fringe | C14: Display, grouping or audit only within the packages (legacy client may use some) | D14: n/a | E14: No
